{
 "actions": [],
 "allow_rename": 1,
 "creation": "2023-10-12 17:51:48.908469",
 "doctype": "DocType",
 "editable_grid": 1,
 "engine": "InnoDB",
 "field_order": [
  "purchase_order"
 ],
 "fields": [
  {
   "fieldname": "purchase_order",
   "fieldtype": "Data",
   "in_list_view": 1,
   "label": "purchase_order"
  }
 ],
 "index_web_pages_for_search": 1,
 "istable": 1,
 "links": [],
 "modified": "2023-10-12 18:36:29.762362",
 "modified_by": "Administrator",
 "module": "APP IAG",
 "name": "project_po_list",
 "owner": "Administrator",
 "permissions": [],
 "sort_field": "modified",
 "sort_order": "DESC",
 "states": []
}